log_color/__init__.py
log_color/colors.py
log_color/formatters.py
log_color/lib.py
log_color/py.typed
log_color/regex.py
log_color-2.1.0.dist-info/licenses/LICENSE
log_color-2.1.0.dist-info/METADATA
log_color-2.1.0.dist-info/WHEEL
log_color-2.1.0.dist-info/top_level.txt
log_color-2.1.0.dist-info/RECORD
