Metadata-Version: 2.4
Name: log_color
Version: 2.1.0
Summary: Simple log formatters for colored output.
Author-email: Brant Watson <oldspiceap@gmail.com>
License:         DO WHAT THE FUCK YOU WANT TO PUBLIC LICENSE
Project-URL: homepage, https://github.com/induane/logcolor
Project-URL: documentation, http://log-color.readthedocs.io/en/latest/
Project-URL: repository, https://github.com/induane/logcolor
Project-URL: changelog, https://github.com/induane/logcolor/blob/master/docs/source/changelog.rst
Keywords: logging,color,formatter
Classifier: Intended Audience :: Developers
Classifier: Operating System :: OS Independent
Classifier: Programming Language :: Python
Classifier: Programming Language :: Python :: 3.8
Classifier: Programming Language :: Python :: 3.9
Classifier: Programming Language :: Python :: 3.10
Classifier: Programming Language :: Python :: 3.11
Classifier: Programming Language :: Python :: 3.12
Classifier: Programming Language :: Python :: 3.13
Classifier: Programming Language :: Python :: 3.14
Classifier: Topic :: Software Development :: Libraries :: Python Modules
Classifier: Typing :: Typed
Requires-Python: >=3.8
License-File: LICENSE
Dynamic: license-file
